streetscape_avs/__init__.py
streetscape_avs/_version.py
streetscape_avs/simpleserver.py
streetscape_avs/streetscape_avs.py
streetscape_avs/static/extension.js
streetscape_avs/static/index.js
streetscape_avs/static/index.js.map
streetscape_avs-0.1.0a4.data/data/etc/jupyter/nbconfig/notebook.d/streetscape_avs.json
streetscape_avs-0.1.0a4.data/data/share/jupyter/nbextensions/streetscape_avs/extension.js
streetscape_avs-0.1.0a4.data/data/share/jupyter/nbextensions/streetscape_avs/index.js
streetscape_avs-0.1.0a4.data/data/share/jupyter/nbextensions/streetscape_avs/index.js.map
streetscape_avs-0.1.0a4.dist-info/METADATA
streetscape_avs-0.1.0a4.dist-info/WHEEL
streetscape_avs-0.1.0a4.dist-info/top_level.txt
streetscape_avs-0.1.0a4.dist-info/RECORD
