Metadata-Version: 2.1
Name: streetscape-avs
Version: 0.1.0a4
Summary: Streetscape.gl Jupyter Widget
Home-page: https://github.com/uber/streetscape.gl
Author: Timothy Wojtaszek
Author-email: twojtasz@uber.com
License: UNKNOWN
Keywords: ipython,jupyter,widgets
Platform: UNKNOWN
Classifier: Development Status :: 4 - Beta
Classifier: Framework :: IPython
Classifier: Intended Audience :: Developers
Classifier: Intended Audience :: Science/Research
Classifier: Topic :: Multimedia :: Graphics
Classifier: Programming Language :: Python :: 3.5
Classifier: Programming Language :: Python :: 3.6
Classifier: Programming Language :: Python :: 3.7
Requires-Dist: ipywidgets (>=7.0.0)
